smoothassert/__init__.py
smoothassert/smoothassert.py
smoothassert-0.1.3.dist-info/LICENSE
smoothassert-0.1.3.dist-info/METADATA
smoothassert-0.1.3.dist-info/WHEEL
smoothassert-0.1.3.dist-info/top_level.txt
smoothassert-0.1.3.dist-info/RECORD
