Metadata-Version: 2.1
Name: smoothassert
Version: 0.1.3
Summary: Custom Assertions for unittest with Pandas.Series and DataFrames. Similarity tests, based on pandas.testing
Home-page: https://github.com/Majszlinger/smoothassert
Author: Tamás Majszlinger
Author-email: tomcsojn@gmail.com
License: UNKNOWN
Platform: UNKNOWN
Classifier: Programming Language :: Python :: 3.7
Classifier: License :: OSI Approved :: GNU General Public License v3 (GPLv3)
Requires-Dist: pandas (>=0.24)
Requires-Dist: numpy (>=1.17)
Requires-Dist: scikit-learn (>=0.21)
